<?xml version="1.0" encoding="UTF-8"?>
<!DOCTYPE plist PUBLIC "-//Apple//DTD PLIST 1.0//EN" "http://www.apple.com/DTDs/PropertyList-1.0.dtd">
<plist version="1.0">
    <array>
        <dict>
            <key>title</key>
            <string>Los Angeles</string>
            <key>description</key>
            <string>Welcome to Los Angeles!</string>
            <key>latitude</key>
            <real>53.573617</real>
            <key>longitude</key>
            <real>3.337965</real>
        </dict>
        <dict>
            <key>title</key>
            <string>New York</string>
            <key>description</key>
            <string>Welcome to New York City!</string>
            <key>latitude</key>
            <real>53.573617</real>
            <key>longitude</key>
            <real>7.168037</real>
        </dict>
        <dict>
            <key>title</key>
            <string>San Francisco</string>
            <key>description</key>
            <string>Welcome to San Francisco!</string>
            <key>latitude</key>
            <real>50.738892</real>
            <key>longitude</key>
            <real>7.168037</real>
        </dict>
        <dict>
            <key>title</key>
            <string>Los Angeles</string>
            <key>description</key>
            <string>Welcome to Los Angeles!</string>
            <key>latitude</key>
            <real>50.738892</real>
            <key>longitude</key>
            <real>3.337965</real>
        </dict>
        <dict>
            <key>x</key>
            <integer>0</integer>
            <key>y</key>
            <integer>0</integer>
            <key>tile</key>
            <array>
                <dict>
                    <key>latitude</key>
                    <real>53,573617</real>
                    <key>longitude</key>
                    <real>3.337965</real>
                </dict>
                <dict>
                    <key>latitude</key>
                    <real>53.573617</real>
                    <key>longitude</key>
                    <real>7.168037</real>
                </dict>
                <dict>
                    <key>latitude</key>
                    <real>50.738892</real>
                    <key>longitude</key>
                    <real>7.168037</real>
                </dict>
                <dict>
                    <key>latitude</key>
                    <real>50,738892</real>
                    <key>longitude</key>
                    <real>3.337965</real>
                </dict>
            </array>
        </dict>
        <dict>
            <key>x</key>
            <integer>1</integer>
            <key>y</key>
            <integer>0</integer>
            <key>tile</key>
            <array>
                <dict>
                    <key>latitude</key>
                    <real>53.573617</real>
                    <key>longitude</key>
                    <real>3.337965</real>
                </dict>
                <dict>
                    <key>latitude</key>
                    <real>53.573617</real>
                    <key>longitude</key>
                    <real>7.168037</real>
                </dict>
                <dict>
                    <key>latitude</key>
                    <real>50.738892</real>
                    <key>longitude</key>
                    <real>7.168037</real>
                </dict>
                <dict>
                    <key>latitude</key>
                    <real>50.738892</real>
                    <key>longitude</key>
                    <real>3.337965</real>
                </dict>
            </array>
        </dict>
    </array>
</plist>
